LICENSE
MANIFEST.in
README.md
VERSION
setup.cfg
setup.py
tests/test_util.py
tests/chrome_store/conftest.py
tests/chrome_store/test_chrome.py
tests/chrome_store/test_cli.py
tests/files/ic.crx
tests/files/ic.zip
tests/files/sample_crx.crx
tests/files/sample_zip.zip
tests/files/script
tests/files/sample_folder/hello
tests/fixtures/cassettes/test_chrome.test_check_status.json
tests/fixtures/cassettes/test_chrome.test_gen_access_token.json
tests/fixtures/cassettes/test_chrome.test_publish.json
tests/fixtures/cassettes/test_chrome.test_redeem_code.json
tests/fixtures/cassettes/test_chrome.test_upload.json
tests/fixtures/cassettes/test_chrome.test_upload_app_not_exists.json
tests/fixtures/cassettes/test_chrome.test_upload_new_item.json
tests/script_parser/test_chrome_functions.py
tests/script_parser/test_cli_script_parser.py
tests/script_parser/test_function_call.py
tests/script_parser/test_generic_functions.py
tests/script_parser/test_parsing_complex.py
tests/script_parser/test_variable_assignment.py
tests/script_parser/test_variable_expansion.py
webstore_manager/__init__.py
webstore_manager/__main__.py
webstore_manager/constants.py
webstore_manager/logging_helper.py
webstore_manager/manager.py
webstore_manager/util.py
webstore_manager/chrome_store/__init__.py
webstore_manager/chrome_store/chrome_store.py
webstore_manager/chrome_store/commands.py
webstore_manager/firefox_store/__init__.py
webstore_manager/firefox_store/commands.py
webstore_manager/firefox_store/firefox_store.py
webstore_manager/script_parser/__init__.py
webstore_manager/script_parser/parser.py
webstore_manager/store/__init__.py
webstore_manager/store/store.py
webstoremgr.egg-info/PKG-INFO
webstoremgr.egg-info/SOURCES.txt
webstoremgr.egg-info/dependency_links.txt
webstoremgr.egg-info/entry_points.txt
webstoremgr.egg-info/requires.txt
webstoremgr.egg-info/top_level.txt