Metadata-Version: 1.1
Name: webstoremgr
Version: 0.7.10
Summary: Publish Chrome and Firefox extensions.
Home-page: https://github.com/melkamar/webstoremgr
Author: Martin Melka
Author-email: melka@avast.com
License: MIT
Keywords: extension,browser,chrome,firefox,store
Platform: UNKNOWN
Classifier: Development Status :: 4 - Beta
Classifier: Intended Audience :: Developers
Classifier: License :: OSI Approved :: MIT License
Classifier: Natural Language :: English
Classifier: Programming Language :: Python
Classifier: Programming Language :: Python :: 3
Classifier: Programming Language :: Python :: 3.5
Classifier: Topic :: Software Development
